diskcache_fernet/__init__.py
diskcache_fernet/cache.py
diskcache_fernet/disk.py
diskcache_fernet/fanout.py
diskcache_fernet/log.py
diskcache_fernet/secret.py
diskcache_fernet-0.1.6.dist-info/METADATA
diskcache_fernet-0.1.6.dist-info/WHEEL
diskcache_fernet-0.1.6.dist-info/licenses/LICENSE
diskcache_fernet-0.1.6.dist-info/RECORD
