Metadata-Version: 2.1
Name: diskcache-fernet
Version: 0.1.6
Project-URL: Repository, https://github.com/phi-friday/diskcache-fernet
Author-email: phi <phi.friday@gmail.com>
License:                                  Apache License
License-File: LICENSE
Classifier: Development Status :: 4 - Beta
Classifier: Programming Language :: Python :: 3
Classifier: Programming Language :: Python :: 3.8
Classifier: Programming Language :: Python :: 3.9
Classifier: Programming Language :: Python :: 3.10
Classifier: Programming Language :: Python :: 3.11
Classifier: Programming Language :: Python :: 3.12
Classifier: Programming Language :: Python :: Implementation :: CPython
Requires-Python: >=3.8
Requires-Dist: cryptography>=41
Requires-Dist: diskcache>=5.6.3
Requires-Dist: typing-extensions>=4.7.0
